{
  "sfGpsDsAuNswButton": {
    "target": "!Os",
    "!.css": {
      "target": "!Os.css",
      "sfGpsDsAuNswButtonCss": "sfGpsDsAuNswButtonCssOs"
    },
    "!.html": {
      "target": "!Os.html"
    },
    "!.js": {
      "target": "!Os.js",
      "sfGpsDsHelpers": "sfGpsDsHelpersOs"
    },
    "!.js-meta.xml": {
      "target": "!Os.js-meta.xml",
      "<isExposed>false</isExposed>": "<isExposed>true</isExposed>\n  <runtimeNamespace>omnistudio</runtimeNamespace>"
    }
  },
  "sfGpsDsAuNswButtonCss": {
    "target": "!Os",
    "button.gen.css": {
      "target": "button.gen.css"
    },
    "!.css": {
      "target": "!Os.css",
      "sfGpsDsAuNswCore": "sfGpsDsAuNswCoreOs"
    },
    "!.js-meta.xml": {
      "target": "!Os.js-meta.xml",
      "<isExposed>false</isExposed>": "<isExposed>true</isExposed>\n  <runtimeNamespace>omnistudio</runtimeNamespace>"
    }
  }
}
